{
    "key": "group_6435013f88b65",
    "title": "Block: Contact Section",
    "fields": [
        {
            "key": "field_6454d70fe0c13",
            "label": "Background Color",
            "name": "section_contact_background_color",
            "aria-label": "",
            "type": "true_false",
            "instructions": "",
            "required": 0,
            "conditional_logic": 0,
            "wrapper": {
                "width": "",
                "class": "",
                "id": ""
            },
            "message": "",
            "default_value": 0,
            "ui_on_text": "orange",
            "ui_off_text": "blue",
            "ui": 1
        },
        {
            "key": "field_6435013f9239b",
            "label": "Text",
            "name": "section_contact_text",
            "aria-label": "",
            "type": "text",
            "instructions": "",
            "required": 0,
            "conditional_logic": 0,
            "wrapper": {
                "width": "",
                "class": "",
                "id": ""
            },
            "default_value": "",
            "maxlength": "",
            "placeholder": "",
            "prepend": "",
            "append": ""
        },
        {
            "key": "field_6435013f923d2",
            "label": "Smaller Text",
            "name": "section_contact_small_text",
            "aria-label": "",
            "type": "text",
            "instructions": "",
            "required": 0,
            "conditional_logic": 0,
            "wrapper": {
                "width": "",
                "class": "",
                "id": ""
            },
            "default_value": "",
            "maxlength": "",
            "placeholder": "",
            "prepend": "",
            "append": ""
        },
        {
            "key": "field_6435013f9243e",
            "label": "Image",
            "name": "section_contact_image",
            "aria-label": "",
            "type": "image",
            "instructions": "",
            "required": 0,
            "conditional_logic": 0,
            "wrapper": {
                "width": "50",
                "class": "",
                "id": ""
            },
            "return_format": "array",
            "library": "all",
            "min_width": "",
            "min_height": "",
            "min_size": "",
            "max_width": "",
            "max_height": "",
            "max_size": "",
            "mime_types": "",
            "preview_size": "thumbnail"
        },
        {
            "key": "field_6454c302d24d1",
            "label": "Image Attributes",
            "name": "section_contact_image_attributes",
            "aria-label": "",
            "type": "group",
            "instructions": "",
            "required": 0,
            "conditional_logic": [
                [
                    {
                        "field": "field_6435013f9243e",
                        "operator": "!=empty"
                    }
                ]
            ],
            "wrapper": {
                "width": "50",
                "class": "",
                "id": ""
            },
            "layout": "block",
            "sub_fields": [
                {
                    "key": "field_6454c323d24d2",
                    "label": "Offset X",
                    "name": "offset_x",
                    "aria-label": "",
                    "type": "range",
                    "instructions": "",
                    "required": 0,
                    "conditional_logic": 0,
                    "wrapper": {
                        "width": "",
                        "class": "",
                        "id": ""
                    },
                    "default_value": 0,
                    "min": -500,
                    "max": 500,
                    "step": "",
                    "prepend": "",
                    "append": ""
                },
                {
                    "key": "field_6454c349d24d3",
                    "label": "Offset Y",
                    "name": "offset_y",
                    "aria-label": "",
                    "type": "range",
                    "instructions": "",
                    "required": 0,
                    "conditional_logic": 0,
                    "wrapper": {
                        "width": "",
                        "class": "",
                        "id": ""
                    },
                    "default_value": 0,
                    "min": -500,
                    "max": 500,
                    "step": "",
                    "prepend": "",
                    "append": ""
                },
                {
                    "key": "field_6454d2cc8aaee",
                    "label": "Width",
                    "name": "width",
                    "aria-label": "",
                    "type": "range",
                    "instructions": "",
                    "required": 0,
                    "conditional_logic": 0,
                    "wrapper": {
                        "width": "",
                        "class": "",
                        "id": ""
                    },
                    "default_value": 350,
                    "min": 0,
                    "max": 1000,
                    "step": "",
                    "prepend": "",
                    "append": ""
                }
            ]
        },
        {
            "key": "field_6454be5c05b88",
            "label": "Links",
            "name": "section_contact_links",
            "aria-label": "",
            "type": "repeater",
            "instructions": "",
            "required": 0,
            "conditional_logic": 0,
            "wrapper": {
                "width": "",
                "class": "",
                "id": ""
            },
            "layout": "block",
            "pagination": 0,
            "min": 0,
            "max": 0,
            "collapsed": "",
            "button_label": "Add Row",
            "rows_per_page": 20,
            "sub_fields": [
                {
                    "key": "field_6454be8405b89",
                    "label": "URL",
                    "name": "url",
                    "aria-label": "",
                    "type": "url",
                    "instructions": "",
                    "required": 0,
                    "conditional_logic": 0,
                    "wrapper": {
                        "width": "33",
                        "class": "",
                        "id": ""
                    },
                    "default_value": "",
                    "placeholder": "",
                    "parent_repeater": "field_6454be5c05b88"
                },
                {
                    "key": "field_6454bede05b8a",
                    "label": "Text",
                    "name": "text",
                    "aria-label": "",
                    "type": "text",
                    "instructions": "",
                    "required": 0,
                    "conditional_logic": 0,
                    "wrapper": {
                        "width": "33",
                        "class": "",
                        "id": ""
                    },
                    "default_value": "",
                    "maxlength": "",
                    "placeholder": "",
                    "prepend": "",
                    "append": "",
                    "parent_repeater": "field_6454be5c05b88"
                },
                {
                    "key": "field_6454bf6abec4c",
                    "label": "Icon",
                    "name": "icon",
                    "aria-label": "",
                    "type": "font-awesome",
                    "instructions": "",
                    "required": 0,
                    "conditional_logic": 0,
                    "wrapper": {
                        "width": "33",
                        "class": "",
                        "id": ""
                    },
                    "icon_sets": [
                        "solid",
                        "regular",
                        "brands"
                    ],
                    "custom_icon_set": "",
                    "default_label": "",
                    "default_value": "",
                    "save_format": "element",
                    "allow_null": 0,
                    "show_preview": 0,
                    "enqueue_fa": 1,
                    "fa_live_preview": "",
                    "choices": [],
                    "parent_repeater": "field_6454be5c05b88"
                }
            ]
        }
    ],
    "location": [
        [
            {
                "param": "block",
                "operator": "==",
                "value": "acf\/oceaa-contact-section"
            }
        ]
    ],
    "menu_order": 0,
    "position": "normal",
    "style": "seamless",
    "label_placement": "top",
    "instruction_placement": "label",
    "hide_on_screen": "",
    "active": true,
    "description": "",
    "show_in_rest": 0
}
